fmri/__init__.py
fmri/_version.py
fmri/optimizer.py
fmri/operators/__init__.py
fmri/operators/fourier.py
fmri/operators/gradient.py
fmri/operators/proximity.py
fmri/operators/svt.py
fmri/operators/time_op.py
fmri/operators/wavelet.py
fmri/operators/weighted.py
fmri/operators/utils/__init__.py
fmri/operators/utils/fft.py
fmri/operators/utils/proxtv.py
fmri/operators/utils/utils.py
fmri/reconstructors/__init__.py
fmri/reconstructors/base.py
fmri/reconstructors/frame_based.py
fmri/reconstructors/time_aware.py
fmri/reconstructors/utils.py
fmri/viz/__init__.py
fmri/viz/images.py
fmri/viz/utils.py
pysap_fmri-0.2.5.dist-info/METADATA
pysap_fmri-0.2.5.dist-info/WHEEL
pysap_fmri-0.2.5.dist-info/top_level.txt
pysap_fmri-0.2.5.dist-info/RECORD
