Metadata-Version: 2.2
Name: pysap-fmri
Version: 0.2.5
Summary: Python Sparse data Analysis Package external fMRI plugin.
Author-email: Pierre-antoine Comby <pierre-antoine.comby@crans.org>
Requires-Dist: modopt
Requires-Dist: numpy
Requires-Dist: tqdm
Requires-Dist: joblib
Requires-Dist: scipy
Requires-Dist: pywavelets
Requires-Dist: mri-nufft[cufinufft]
Provides-Extra: test
Requires-Dist: pytest; extra == "test"
Requires-Dist: pytest-cov; extra == "test"
Requires-Dist: pytest-xdist; extra == "test"
Requires-Dist: pytest-sugar; extra == "test"
Provides-Extra: doc
Requires-Dist: pydata-sphinx-theme; extra == "doc"
Requires-Dist: numpydoc; extra == "doc"
Requires-Dist: sphinx_gallery; extra == "doc"
Requires-Dist: sphinx; extra == "doc"
Requires-Dist: sphinx-autoapi; extra == "doc"
Provides-Extra: dev
Requires-Dist: ruff; extra == "dev"
